{"version": 0.6, "generator": "Overpass API 0.7.61.5 4133829e", "osm3s": {"timestamp_osm_base": "2023-10-31T20:29:00Z", "copyright": "The data included in this document is from www.openstreetmap.org. The data is made available under ODbL."}, "elements": [{"type": "node", "id": 1042137860, "lat": -18.4722004, "lon": -70.3206024, "tags": {"aeroway": "helipad", "name": "Naval Heliport", "source": "ourairports.com"}}, {"type": "node", "id": 2024406742, "lat": -12.0509849, "lon": -75.229339, "tags": {"aeroway": "helipad"}}, {"type": "node", "id": 2478174771, "lat": -13.0509045, "lon": -73.7022127, "tags": {"aeroway": "helipad", "source": "bing"}}, {"type": "node", "id": 3183286973, "lat": -11.8482186, "lon": -72.9387464, "tags": {"aeroway": "helipad"}}, {"type": "node", "id": 3183286976, "lat": -11.8477326, "lon": -72.9388879, "tags": {"aeroway": "helipad"}}, {"type": "node", "id": 3183286977, "lat": -11.8475278, "lon": -72.9388682, "tags": {"aeroway": "helipad"}}, {"type": "node", "id": 3438666697, "lat": -18.4828465, "lon": -70.3129932, "tags": {"aeroway": "helipad"}}, {"type": "node", "id": 4041994435, "lat": -12.0632155, "lon": -77.1230123, "tags": {"aeroway": "helipad"}}, {"type": "node", "id": 4042114119, "lat": -12.0593785, "lon": -77.1209832, "tags": {"aeroway": "helipad"}}, {"type": "node", "id": 4227512245, "lat": -10.1021247, "lon": -78.181387, "tags": {"aeroway": "helipad"}}, {"type": "node", "id": 4567210942, "lat": -12.1010746, "lon": -76.9836792, "tags": {"aeroway": "helipad"}}, {"type": "node", "id": 5274527739, "lat": -19.1575024, "lon": -70.1850819, "tags": {"aeroway": "helipad", "source": "Bing"}}, {"type": "node", "id": 7363523306, "lat": -13.1621735, "lon": -72.5236087, "tags": {"aeroway": "helipad"}}, {"type": "node", "id": 7490456094, "lat": -12.1612557, "lon": -72.992826, "tags": {"aeroway": "helipad"}}, {"type": "node", "id": 7490870707, "lat": -11.8519097, "lon": -72.941322, "tags": {"aeroway": "helipad"}}, {"type": "node", "id": 7490870708, "lat": -11.8530596, "lon": -72.942314, "tags": {"aeroway": "helipad"}}, {"type": "node", "id": 7490870709, "lat": -11.8531749, "lon": -72.9415761, "tags": {"aeroway": "helipad"}}, {"type": "node", "id": 7490870710, "lat": -11.8537141, "lon": -72.9420945, "tags": {"aeroway": "helipad"}}, {"type": "node", "id": 7490870711, "lat": -11.8538354, "lon": -72.9413708, "tags": {"aeroway": "helipad"}}, {"type": "node", "id": 7494125624, "lat": -11.880394, "lon": -72.8206293, "tags": {"aeroway": "helipad"}}, {"type": "node", "id": 7513469047, "lat": -11.6538734, "lon": -73.0585214, "tags": {"aeroway": "helipad"}}, {"type": "node", "id": 7517411474, "lat": -13.2401621, "lon": -70.7783666, "tags": {"aeroway": "helipad"}}, {"type": "node", "id": 7517411475, "lat": -13.2407783, "lon": -70.7774627, "tags": {"aeroway": "helipad"}}, {"type": "node", "id": 7517411476, "lat": -13.2409402, "lon": -70.7782673, "tags": {"aeroway": "helipad"}}, {"type": "node", "id": 7517411477, "lat": -13.2415198, "lon": -70.7774037, "tags": {"aeroway": "helipad"}}, {"type": "node", "id": 9400398284, "lat": -12.7647907, "lon": -73.654778, "tags": {"aeroway": "helipad"}}, {"type": "node", "id": 9435454716, "lat": -12.5293327, "lon": -73.8310378, "tags": {"aeroway": "helipad"}}, {"type": "node", "id": 9435454717, "lat": -12.5231756, "lon": -73.8306202, "tags": {"aeroway": "helipad"}}, {"type": "node", "id": 9435454718, "lat": -12.5232328, "lon": -73.8302443, "tags": {"aeroway": "helipad"}}, {"type": "node", "id": 9435454719, "lat": -12.5235757, "lon": -73.830269, "tags": {"aeroway": "helipad"}}, {"type": "node", "id": 9435454720, "lat": -12.5239667, "lon": -73.8303429, "tags": {"aeroway": "helipad"}}, {"type": "node", "id": 9435454721, "lat": -12.5243095, "lon": -73.8304076, "tags": {"aeroway": "helipad"}}, {"type": "node", "id": 9496885792, "lat": -12.1196075, "lon": -77.0461022, "tags": {"aeroway": "helipad", "name": "Helipuerto Municipal Rodolfo Le\u00f3n Gavil\u00e1n", "source": "https://www.youtube.com/watch?v=vqGUrv1vDCg"}}, {"type": "node", "id": 9501776162, "lat": -12.0974686, "lon": -77.0379632, "tags": {"aeroway": "helipad"}}, {"type": "node", "id": 9501814520, "lat": -12.0979332, "lon": -77.0477412, "tags": {"aeroway": "helipad"}}, {"type": "node", "id": 9548355255, "lat": -12.0979356, "lon": -77.0165897, "tags": {"aeroway": "helipad"}}, {"type": "node", "id": 9586300283, "lat": -12.0829915, "lon": -76.9674939, "tags": {"aeroway": "helipad"}}, {"type": "node", "id": 10080694766, "lat": -14.1028742, "lon": -72.2762253, "tags": {"aeroway": "helipad", "description": "Helipuerto SPLB. operaciones a\u00e9reas Las Bambas\n", "ele": "3762", "ref": "Helipuerto Las Bambas SPLB"}}, {"type": "node", "id": 10560324246, "lat": -12.0276621, "lon": -77.1044395, "tags": {"aeroway": "helipad"}}, {"type": "node", "id": 10560324247, "lat": -12.027876, "lon": -77.1043409, "tags": {"aeroway": "helipad"}}, {"type": "node", "id": 10560324248, "lat": -12.0274933, "lon": -77.1040267, "tags": {"aeroway": "helipad"}}, {"type": "node", "id": 10560324249, "lat": -12.0276832, "lon": -77.1039404, "tags": {"aeroway": "helipad"}}, {"type": "node", "id": 10560681470, "lat": -12.0088897, "lon": -77.1158213, "tags": {"aeroway": "helipad"}}, {"type": "node", "id": 10560681471, "lat": -12.0090734, "lon": -77.1157274, "tags": {"aeroway": "helipad"}}, {"type": "node", "id": 10560681474, "lat": -12.0099742, "lon": -77.1162348, "tags": {"aeroway": "helipad"}}, {"type": "node", "id": 10560681479, "lat": -12.0177279, "lon": -77.1135366, "tags": {"aeroway": "helipad"}}, {"type": "node", "id": 10560681480, "lat": -12.0176909, "lon": -77.1131473, "tags": {"aeroway": "helipad"}}, {"type": "node", "id": 10560681481, "lat": -12.0178358, "lon": -77.1129818, "tags": {"aeroway": "helipad"}}, {"type": "node", "id": 10560681482, "lat": -12.0179296, "lon": -77.1128365, "tags": {"aeroway": "helipad"}}, {"type": "node", "id": 10560681483, "lat": -12.0180234, "lon": -77.1127029, "tags": {"aeroway": "helipad"}}, {"type": "node", "id": 10560681484, "lat": -12.0181512, "lon": -77.1125489, "tags": {"aeroway": "helipad"}}, {"type": "node", "id": 10560681485, "lat": -12.0182507, "lon": -77.1123979, "tags": {"aeroway": "helipad"}}, {"type": "node", "id": 10560681486, "lat": -12.0183956, "lon": -77.1122091, "tags": {"aeroway": "helipad"}}, {"type": "node", "id": 10560681487, "lat": -12.0187223, "lon": -77.1116078, "tags": {"aeroway": "helipad"}}, {"type": "node", "id": 10560681488, "lat": -12.0175119, "lon": -77.1121742, "tags": {"aeroway": "helipad"}}, {"type": "node", "id": 10560681489, "lat": -12.0175119, "lon": -77.1125838, "tags": {"aeroway": "helipad"}}, {"type": "node", "id": 10560681490, "lat": -12.0178188, "lon": -77.1121916, "tags": {"aeroway": "helipad"}}, {"type": "node", "id": 10560681491, "lat": -12.017546, "lon": -77.1123775, "tags": {"aeroway": "helipad"}}, {"type": "node", "id": 10560681492, "lat": -12.0292732, "lon": -77.1054941, "tags": {"aeroway": "helipad"}}, {"type": "node", "id": 10560681493, "lat": -12.0337585, "lon": -77.1053212, "tags": {"aeroway": "helipad"}}, {"type": "node", "id": 10560681494, "lat": -12.0337375, "lon": -77.1050744, "tags": {"aeroway": "helipad"}}, {"type": "node", "id": 10560681495, "lat": -12.033671, "lon": -77.104867, "tags": {"aeroway": "helipad"}}, {"type": "node", "id": 10560681496, "lat": -12.0337095, "lon": -77.1055143, "tags": {"aeroway": "helipad"}}, {"type": "node", "id": 10774551338, "lat": -12.651499, "lon": -73.0526749, "tags": {"aeroway": "helipad"}}, {"type": "node", "id": 11079624600, "lat": -13.2237479, "lon": -76.2714116, "tags": {"aeroway": "helipad", "surface": "paved"}}, {"type": "way", "id": 130680165, "center": {"lat": -17.6936757, "lon": -71.3391268}, "nodes": [1438562204, 1438562225, 8461187540, 1438562215, 1438562204], "tags": {"aeroway": "helipad"}}, {"type": "way", "id": 169146979, "center": {"lat": -13.5424455, "lon": -72.7060017}, "nodes": [1803142504, 1803142509, 1803142514, 1803142518, 1803142522, 1803142524, 1803142526, 1803142528, 1803142527, 1803142525, 1803142523, 1803142521, 1803142516, 1803142511, 1803142506, 1803142502, 1803142504], "tags": {"aeroway": "helipad"}}, {"type": "way", "id": 180521662, "center": {"lat": -12.0601849, "lon": -77.0922742}, "nodes": [1909464703, 1909464695, 1909464705, 1909464706, 1909464703], "tags": {"aeroway": "helipad", "name": "Helipuerto Hospital Naval \"Santiago T\u00e1vara\"", "name:en": "Heliport of \"Santiago T\u00e1bara\" Naval Hospital", "ref": "Hospital Naval"}}, {"type": "way", "id": 271130351, "center": {"lat": -18.4757662, "lon": -70.3227474}, "nodes": [2760931991, 2760932000, 2760931997, 2760931984, 2760931991], "tags": {"aeroway": "helipad"}}, {"type": "way", "id": 271155382, "center": {"lat": -19.5985817, "lon": -70.2176374}, "nodes": [2761147619, 2761147621, 2761147624, 2761147623, 2761147620, 2761147617, 2761147614, 2761147611, 2761147607, 2761147609, 2761147613, 2761147615, 2761147619], "tags": {"aeroway": "helipad"}}, {"type": "way", "id": 289969164, "center": {"lat": -10.7338338, "lon": -73.7529967}, "nodes": [2935024817, 2935024818, 2935024819, 2935024820, 2935024817], "tags": {"aeroway": "helipad"}}, {"type": "way", "id": 293806751, "center": {"lat": -12.0324733, "lon": -77.1449625}, "nodes": [2973913273, 2973913274, 2973913275, 2973913276, 2973913277, 2973913278, 2973913279, 2973913280, 2973913281, 2973913282, 2973913273], "tags": {"aeroway": "helipad"}}, {"type": "way", "id": 376741869, "center": {"lat": -11.9589831, "lon": -76.9990993}, "nodes": [3801322377, 8735302007, 8735302006, 3801322378, 8735302005, 8735302004, 8735302003, 3801322380, 8735302002, 8735302001, 8735302000, 8735301999, 3801322377], "tags": {"aeroway": "helipad", "name": "Canto Grande"}}, {"type": "way", "id": 385012337, "center": {"lat": -12.0704626, "lon": -77.1053262}, "nodes": [3883665308, 3883665309, 3883665310, 3883665311, 3883665308], "tags": {"aeroway": "helipad", "operator": "Marina de Guerra del Per\u00fa", "surface": "concrete"}}, {"type": "way", "id": 396784675, "center": {"lat": -12.0174082, "lon": -77.1137429}, "nodes": [3996224710, 3996224752, 3996224723, 3996224702, 3996224741, 3996224716, 3996224735, 3996224748, 3996224698, 3996224706, 3996224743, 3996224688, 3996224750, 3996224714, 3996224733, 3996224690, 3996224707, 3996224710], "tags": {"aeroway": "helipad"}}, {"type": "way", "id": 398908699, "center": {"lat": -11.5468008, "lon": -73.1422851}, "nodes": [4016439488, 4016439490, 4016439491, 4016439489, 4016439488], "tags": {"aeroway": "helipad"}}, {"type": "way", "id": 398908700, "center": {"lat": -11.5474996, "lon": -73.1423871}, "nodes": [4016439492, 4016439493, 4016439495, 4016439494, 4016439492], "tags": {"aeroway": "helipad"}}, {"type": "way", "id": 398908701, "center": {"lat": -11.5488105, "lon": -73.1425455}, "nodes": [4016439533, 4016439535, 4016439538, 4016439537, 4016439533], "tags": {"aeroway": "helipad"}}, {"type": "way", "id": 398908702, "center": {"lat": -11.5494798, "lon": -73.1426278}, "nodes": [4016439549, 4016439550, 4016439551, 4016439548, 4016439549], "tags": {"aeroway": "helipad"}}, {"type": "way", "id": 398908703, "center": {"lat": -11.5508598, "lon": -73.1424901}, "nodes": [4016439554, 4016439555, 4016439557, 4016439556, 4016439554], "tags": {"aeroway": "helipad"}}, {"type": "way", "id": 405565202, "center": {"lat": -12.1135321, "lon": -77.0332657}, "nodes": [4077427086, 4077427087, 4077427088, 4077431289, 4077431290, 4077431291, 4077431292, 4077431293, 4077427075, 4077427076, 4077427079, 4077427080, 4077427081, 4077427082, 4077427083, 4077427084, 4077427085, 4077427077, 4077427078, 4077427086], "tags": {"aeroway": "helipad", "min_height": "17"}}, {"type": "way", "id": 456096261, "center": {"lat": -14.2684279, "lon": -70.3193123}, "nodes": [4523744369, 4523744371, 4523744386, 4523744385, 4523744395, 4523744403, 4523744387, 4523744369], "tags": {"aeroway": "helipad"}}, {"type": "way", "id": 472445250, "center": {"lat": -13.533273, "lon": -71.9787461}, "nodes": [4666539034, 4666539035, 4666539036, 4666539037, 4666539038, 4666539039, 4666539040, 4666539041, 4666539042, 4666539043, 4666539044, 4666539045, 4666539046, 4666539030, 4666539031, 4666539032, 4666539033, 4666539028, 4666539029, 4666539034], "tags": {"aeroway": "helipad"}}, {"type": "way", "id": 504577753, "center": {"lat": -12.6483672, "lon": -73.0526818}, "nodes": [4947232525, 4947232416, 4947232521, 4947232415, 4947232524, 4947232414, 4947232420, 4947232413, 4947232523, 4947232412, 4947232419, 4947232411, 4947232522, 4947232410, 4947232418, 4947232417, 4947232525], "tags": {"aeroway": "helipad", "source": "bing"}}, {"type": "way", "id": 504600889, "center": {"lat": -12.8430159, "lon": -73.4552856}, "nodes": [7676151278, 7676151279, 7676151280, 7676151281, 7676151282, 7676151283, 4947483877, 4947483876, 4947483875, 4947483874, 7676151274, 7676151275, 7676151276, 7676151277, 4947483873, 4947483872, 4947483871, 4947483870, 4947483869, 7676151278], "tags": {"aeroway": "helipad"}}, {"type": "way", "id": 504600897, "center": {"lat": -12.5731287, "lon": -73.1629368}, "nodes": [4947484581, 4947484580, 4947484579, 4947484578, 4947484577, 4947484576, 4947484575, 4947484574, 4947484581], "tags": {"aeroway": "helipad", "source": "bing"}}, {"type": "way", "id": 504600932, "center": {"lat": -12.5101284, "lon": -73.1021012}, "nodes": [4947484968, 4947484967, 4947484966, 4947484965, 4947484964, 4947484963, 4947484962, 4947484961, 4947484968], "tags": {"aeroway": "helipad", "source": "bing"}}, {"type": "way", "id": 505314343, "center": {"lat": -13.1529041, "lon": -74.2045179}, "nodes": [4952823578, 4952823579, 4952823561, 4952823562, 4952823563, 4952823564, 4952823565, 4952823566, 4952823567, 4952823576, 4952823577, 4952823568, 4952823569, 4952823570, 4952823571, 4952823572, 4952823573, 4952823574, 4952823575, 4952823578], "tags": {"aeroway": "helipad"}}, {"type": "way", "id": 505314345, "center": {"lat": -13.1524201, "lon": -74.2043146}, "nodes": [4952823596, 4952823597, 4952823598, 4952823580, 4952823581, 4952823582, 4952823583, 4952823584, 4952823585, 4952823586, 4952823594, 4952823595, 4952823587, 4952823588, 4952823589, 4952823590, 4952823591, 4952823592, 4952823593, 4952823596], "tags": {"aeroway": "helipad"}}, {"type": "way", "id": 505314350, "center": {"lat": -13.1517075, "lon": -74.2040284}, "nodes": [4952823628, 4952823629, 4952823630, 4952823631, 4952823613, 4952823614, 4952823615, 4952823616, 4952823617, 4952823624, 4952823625, 4952823626, 4952823627, 4952823618, 4952823619, 4952823620, 4952823621, 4952823622, 4952823623, 4952823628], "tags": {"aeroway": "helipad"}}, {"type": "way", "id": 544844274, "center": {"lat": -12.7854505, "lon": -73.3709137}, "nodes": [5266370857, 5266370858, 5266370859, 5266370860, 5266370861, 5266370862, 5266370863, 5266370864, 5266370865, 5266370866, 5266370848, 5266370851, 5266370852, 5266370853, 5266370854, 5266370855, 5266370856, 5266370849, 5266370850, 5266370857], "tags": {"aeroway": "helipad"}}, {"type": "way", "id": 551511660, "center": {"lat": -10.9067229, "lon": -77.2350625}, "nodes": [5326206714, 5326206712, 5326206711, 5326206710, 5326206709, 5326206708, 5326206713, 5326206707, 5326206706, 5326206705, 5326206704, 5326206715, 5326206703, 5326206702, 5326206701, 5326206700, 5326206714], "tags": {"aeroway": "helipad"}}, {"type": "way", "id": 591634466, "center": {"lat": -12.1681738, "lon": -77.0069227}, "nodes": [5648011850, 5648011851, 5648011852, 5648011853, 5648011854, 5648011850], "tags": {"aeroway": "helipad"}}, {"type": "way", "id": 616655709, "center": {"lat": -12.0441901, "lon": -77.0289955}, "nodes": [5829820691, 5829820692, 5829820693, 5829820694, 5829820691], "tags": {"aeroway": "helipad"}}, {"type": "way", "id": 621877609, "center": {"lat": -12.1010709, "lon": -76.9837009}, "nodes": [5874948989, 5874948990, 5874948991, 5874948992, 5874948993, 5874948994, 5874948995, 5874948877, 5874948878, 5874948881, 5874948882, 5874948883, 5874948884, 5874948985, 5874948986, 5874948987, 5874948988, 5874948879, 5874948880, 5874948989], "tags": {"aeroway": "helipad"}}, {"type": "way", "id": 640388182, "center": {"lat": -12.0270271, "lon": -77.0415292}, "nodes": [6032851588, 6032851589, 6032851590, 6032851591, 6032851592, 6032851593, 6032849475, 6032849476, 6032849479, 6032849480, 6032849481, 6032849482, 6032849483, 6032849484, 6032851585, 6032851586, 6032851587, 6032849477, 6032849478, 6032851588], "tags": {"aeroway": "helipad"}}, {"type": "way", "id": 663377570, "center": {"lat": -12.0401548, "lon": -76.9929417}, "nodes": [6209412002, 6209412003, 5935554995, 6209412004, 6209412002], "tags": {"aeroway": "helipad"}}, {"type": "way", "id": 732692568, "center": {"lat": -14.7481511, "lon": -71.5890225}, "nodes": [6860958040, 6860958041, 6860958042, 6860958043, 6860958040], "tags": {"aeroway": "helipad"}}, {"type": "way", "id": 768705193, "center": {"lat": -14.0738829, "lon": -75.7425891}, "nodes": [7176663557, 7176663558, 7176663559, 7176663560, 7176663557], "tags": {"aeroway": "helipad"}}, {"type": "way", "id": 786319353, "center": {"lat": -11.747561, "lon": -77.1666226}, "nodes": [7352167734, 7352167735, 7352167736, 7352167737, 7352167738, 7352167739, 7352167740, 7352167741, 7352167723, 7352167724, 7352167727, 7352167728, 7352167729, 7352167730, 7352167731, 7352167732, 7352167733, 7352167725, 7352167726, 7352167734], "tags": {"aeroway": "helipad", "operator": "Marina de Guerra del Per\u00fa", "surface": "asphalt"}}, {"type": "way", "id": 786319354, "center": {"lat": -11.7479041, "lon": -77.1664344}, "nodes": [7352167742, 7352167743, 7352167744, 7352167745, 7352167746, 7352167747, 7352167748, 7352167749, 7352167750, 7352167751, 7352167752, 7352167753, 7352167754, 7352167755, 7352167756, 7352167757, 7352167758, 7352167759, 7352167760, 7352167742], "tags": {"aeroway": "helipad", "operator": "Marina de Guerra del Per\u00fa", "surface": "asphalt"}}, {"type": "way", "id": 786319425, "center": {"lat": -11.7437756, "lon": -77.1666545}, "nodes": [7352168160, 7352168161, 7352168162, 7352168163, 7352168160], "tags": {"aeroway": "helipad", "operator": "Marina de Guerra del Per\u00fa", "surface": "asphalt"}}, {"type": "way", "id": 786319426, "center": {"lat": -11.7438912, "lon": -77.1670977}, "nodes": [7352168164, 7352168165, 7352168166, 7352168167, 7352168164], "tags": {"aeroway": "helipad", "operator": "Marina de Guerra del Per\u00fa", "surface": "concrete"}}, {"type": "way", "id": 789881429, "center": {"lat": -12.8611946, "lon": -72.7015799}, "nodes": [7385129221, 7385129222, 7385129223, 7385129224, 7385129206, 7385129207, 7385129208, 7385129209, 7385129210, 7385129216, 7385129217, 7385129218, 7385129219, 7385129220, 7385129211, 7385129212, 7385129213, 7385129214, 7385129215, 7385129221], "tags": {"aeroway": "helipad"}}, {"type": "way", "id": 789881430, "center": {"lat": -12.8610231, "lon": -72.7013649}, "nodes": [7385129225, 7385129226, 7385129227, 7385129228, 7385129225], "tags": {"aeroway": "helipad"}}, {"type": "way", "id": 789881431, "center": {"lat": -12.8618969, "lon": -72.7008317}, "nodes": [7385129241, 7385129242, 7385129243, 7385129244, 7385129245, 7385129246, 7385129247, 7385129229, 7385129230, 7385129231, 7385129232, 7385129237, 7385129238, 7385129239, 7385129240, 7385129233, 7385129236, 7385129234, 7385129235, 7385129241], "tags": {"aeroway": "helipad"}}, {"type": "way", "id": 800805612, "center": {"lat": -11.9189966, "lon": -72.9308513}, "nodes": [7490164528, 7490164529, 7490164530, 7490164531, 7490164532, 7490164533, 7490164534, 7490164535, 7490164536, 7490164537, 7490164538, 7490164520, 7490164523, 7490164524, 7490164525, 7490164526, 7490164527, 7490164521, 7490164522, 7490164528], "tags": {"aeroway": "helipad"}}, {"type": "way", "id": 800805613, "center": {"lat": -11.9181635, "lon": -72.9310743}, "nodes": [7490164548, 7490164549, 7490164550, 7490164551, 7490164552, 7490164553, 7490164554, 7490164555, 7490164556, 7490164557, 7490164539, 7490164542, 7490164543, 7490164544, 7490164545, 7490164546, 7490164547, 7490164540, 7490164541, 7490164548], "tags": {"aeroway": "helipad"}}, {"type": "way", "id": 800836380, "center": {"lat": -11.8862328, "lon": -72.8665937}, "nodes": [7490439857, 7490439858, 7490439859, 7490439860, 7490439857], "tags": {"aeroway": "helipad"}}, {"type": "way", "id": 800849269, "center": {"lat": -11.9763723, "lon": -72.9657112}, "nodes": [7490569585, 7490569586, 7490569587, 7490569588, 7490569589, 7490569590, 7490569591, 7490569592, 7490569593, 7490569575, 7490569576, 7490569580, 7490569581, 7490569582, 7490569583, 7490569584, 7490569577, 7490569578, 7490569579, 7490569585], "tags": {"aeroway": "helipad"}}, {"type": "way", "id": 801002579, "center": {"lat": -11.8842139, "lon": -72.9492211}, "nodes": [7492146334, 7492146335, 7492146336, 7492146337, 7492146334], "tags": {"aeroway": "helipad"}}, {"type": "way", "id": 801015364, "center": {"lat": -11.7674585, "lon": -72.7781264}, "nodes": [7492259193, 7492259194, 7492259195, 7492259196, 7492259193], "tags": {"aeroway": "helipad"}}, {"type": "way", "id": 801278502, "center": {"lat": -11.8904597, "lon": -72.8066345}, "nodes": [7493922824, 7493922825, 7493922826, 7493922827, 7493922824], "tags": {"aeroway": "helipad"}}, {"type": "way", "id": 801312528, "center": {"lat": -11.8802807, "lon": -72.6492146}, "nodes": [7494400055, 7494400056, 7494400057, 7494400058, 7494400055], "tags": {"aeroway": "helipad"}}, {"type": "way", "id": 802958207, "center": {"lat": -11.5218484, "lon": -73.2079684}, "nodes": [7511071516, 7511071517, 7511071518, 7511071519, 7511071516], "tags": {"aeroway": "helipad"}}, {"type": "way", "id": 803044034, "center": {"lat": -11.5462921, "lon": -73.1503126}, "nodes": [7511863375, 7511863376, 7511863377, 7511863378, 7511863375], "tags": {"aeroway": "helipad"}}, {"type": "way", "id": 803070776, "center": {"lat": -11.5794891, "lon": -73.1660338}, "nodes": [7511962351, 7511962350, 7511962349, 7511962348, 7511962351], "tags": {"aeroway": "helipad"}}, {"type": "way", "id": 803126703, "center": {"lat": -11.7326735, "lon": -72.9425884}, "nodes": [7512545806, 7512545813, 7512545807, 7512545808, 7512545809, 7512545806], "tags": {"aeroway": "helipad"}}, {"type": "way", "id": 803830044, "center": {"lat": -12.450539, "lon": -73.0430536}, "nodes": [7519126711, 7519126712, 7519126713, 7519126714, 7519126715, 7519126716, 7519126717, 7519126699, 7519126700, 7519126701, 7519126702, 7519126707, 7519126708, 7519126709, 7519126710, 7519126703, 7519126704, 7519126705, 7519126706, 7519126711], "tags": {"aeroway": "helipad"}}, {"type": "way", "id": 803845902, "center": {"lat": -12.325082, "lon": -73.0434371}, "nodes": [7519332806, 7519332807, 7519332808, 7519332809, 7519332810, 7519332792, 7519332793, 7519332794, 7519332795, 7519332796, 7519332802, 7519332803, 7519332804, 7519332805, 7519332797, 7519332798, 7519332799, 7519332800, 7519332801, 7519332806], "tags": {"aeroway": "helipad"}}, {"type": "way", "id": 804694251, "center": {"lat": -12.0801444, "lon": -77.2098991}, "nodes": [7526818243, 7526818242, 7526818241, 7526818240, 7526818239, 7526818238, 7526818237, 7526818236, 7526818235, 7526818244, 7526818234, 7526818233, 7526818232, 7526818231, 7526818230, 7526818229, 7526818228, 7526818227, 7526818243], "tags": {"aeroway": "helipad", "operator": "Marina de Guerra del Per\u00fa", "surface": "ground"}}, {"type": "way", "id": 806998108, "center": {"lat": -12.7601369, "lon": -76.6033037}, "nodes": [7546476060, 7546476059, 7546476058, 7546476057, 7546476056, 7546476055, 7546476054, 7546476053, 7546476060], "tags": {"aeroway": "helipad", "operator": "Boulevard de Asia"}}, {"type": "way", "id": 869826377, "center": {"lat": -12.0588612, "lon": -77.0220954}, "nodes": [8104571261, 8104571262, 8104571263, 8104571264, 8104571265, 8104571266, 8104571267, 8104571268, 8104571250, 8104571251, 8104571254, 8104571255, 8104571256, 8104571257, 8104571258, 8104571259, 8104571260, 8104571252, 8104571253, 8104571261], "tags": {"aeroway": "helipad"}}, {"type": "way", "id": 878820345, "center": {"lat": -17.7070741, "lon": -70.8473784}, "nodes": [8175726108, 8175726107, 8175726106, 8175726105, 8175726108], "tags": {"aeroway": "helipad"}}, {"type": "way", "id": 1008734390, "center": {"lat": -12.0894484, "lon": -77.0227078}, "nodes": [9307296975, 9307296976, 9307296977, 9307296978, 9307296979, 9307296980, 9307296981, 9307296982, 9307296983, 9307296984, 9307296985, 9307296986, 9307296987, 9307296988, 9307296989, 9307296990, 9307296991, 9307296992, 9307296993, 9307296975], "tags": {"aeroway": "helipad", "min_height": "81"}}, {"type": "way", "id": 1009007275, "center": {"lat": -17.0126413, "lon": -72.0353712}, "nodes": [9309779939, 9309779940, 9309779941, 9309779942, 9309779939], "tags": {"aeroway": "helipad"}}, {"type": "way", "id": 1047348626, "center": {"lat": -11.695707, "lon": -72.9523664}, "nodes": [9630719230, 9630719231, 9630719232, 9630719233, 9630719234, 9630719230], "tags": {"aeroway": "helipad"}}, {"type": "way", "id": 1050686701, "center": {"lat": -11.2973428, "lon": -72.9900668}, "nodes": [9655226932, 9655226931, 9655226924, 9655226930, 9655226929, 9655226932], "tags": {"aeroway": "helipad"}}, {"type": "way", "id": 1053073823, "center": {"lat": -12.4600938, "lon": -72.9594811}, "nodes": [9677756344, 9677756345, 9677756346, 9677756347, 9677756344], "tags": {"aeroway": "helipad"}}, {"type": "way", "id": 1053190591, "center": {"lat": -11.5523228, "lon": -73.1467105}, "nodes": [9678743515, 9678743514, 9678743513, 9678743512, 9678743515], "tags": {"aeroway": "helipad"}}, {"type": "way", "id": 1053204113, "center": {"lat": -11.5519031, "lon": -73.1470548}, "nodes": [9678869439, 9678869440, 9678869452, 9678869441, 9678869442, 9678869439], "tags": {"aeroway": "helipad"}}, {"type": "way", "id": 1053204120, "center": {"lat": -11.5513054, "lon": -73.1475409}, "nodes": [9678869475, 9678869479, 9678869476, 9678869477, 9678869478, 9678869475], "tags": {"aeroway": "helipad"}}, {"type": "way", "id": 1053518502, "center": {"lat": -11.6918657, "lon": -72.9505625}, "nodes": [9681739438, 9681739439, 9681739440, 9681739441, 9681739438], "tags": {"aeroway": "helipad"}}, {"type": "way", "id": 1060375472, "center": {"lat": -12.1036131, "lon": -77.0657087}, "nodes": [9742332734, 9742332735, 9742332736, 9742332737, 9742332763, 9742332768, 9742332764, 9742332734], "tags": {"aeroway": "helipad", "surface": "concrete"}}, {"type": "way", "id": 1060942137, "center": {"lat": -14.6818523, "lon": -75.1342018}, "nodes": [9748065006, 9748065003, 9748065004, 9748065005, 9748065006], "tags": {"aeroway": "helipad"}}, {"type": "way", "id": 1125504272, "center": {"lat": -13.1628811, "lon": -74.200173}, "nodes": [10292253807, 10292253808, 10292258109, 10292258110, 10292258111, 10292258112, 10292258113, 10292258114, 10292253807], "tags": {"aeroway": "helipad"}}, {"type": "way", "id": 1134960147, "center": {"lat": -16.8238039, "lon": -71.8536862}, "nodes": [10580049810, 10580049811, 10580049812, 10580049813, 10580049810], "tags": {"aeroway": "helipad"}}, {"type": "way", "id": 1134960148, "center": {"lat": -16.8211747, "lon": -71.8538205}, "nodes": [10580049814, 10580049815, 10580049816, 10580049817, 10580049814], "tags": {"aeroway": "helipad"}}, {"type": "way", "id": 1134960149, "center": {"lat": -16.8217024, "lon": -71.8537089}, "nodes": [10580049818, 10580049819, 10580049820, 10580049821, 10580049818], "tags": {"aeroway": "helipad"}}, {"type": "way", "id": 1134960150, "center": {"lat": -16.8212677, "lon": -71.8526333}, "nodes": [10580049822, 10580049823, 10580049824, 10580049825, 10580049822], "tags": {"aeroway": "helipad"}}, {"type": "way", "id": 1134960151, "center": {"lat": -16.8226412, "lon": -71.8523929}, "nodes": [10580049826, 10580049827, 10580049828, 10580049829, 10580049826], "tags": {"aeroway": "helipad"}}, {"type": "way", "id": 1139104368, "center": {"lat": -18.5086493, "lon": -70.2848566}, "nodes": [10617329720, 10617329721, 10617329722, 10617329723, 10617329720], "tags": {"aeroway": "helipad", "lit": "yes"}}, {"type": "way", "id": 1157714197, "center": {"lat": -11.4836704, "lon": -74.4836749}, "nodes": [10766545184, 10766545185, 10766545186, 10766545187, 10766545188, 10766545189, 10766545190, 10766545191, 10766545192, 10766545193, 10766545194, 10766545195, 10766545196, 10766545184], "tags": {"aeroway": "helipad"}}, {"type": "way", "id": 1161861882, "center": {"lat": -18.749161, "lon": -70.3363107}, "nodes": [10806175402, 10806175403, 10806175404, 10806190805, 10806175402], "tags": {"aeroway": "helipad", "name": "Helipuerto Caleta V\u00edtor", "surface": "concrete"}}, {"type": "way", "id": 1198443037, "center": {"lat": -13.0016363, "lon": -73.5027162}, "nodes": [11117434025, 11117434026, 11117434008, 11117434009, 11117434010, 11117434011, 11117434012, 11117434013, 11117434014, 11117434022, 11117434023, 11117434024, 11117434015, 11117434016, 11117434017, 11117434018, 11117434019, 11117434020, 11117434021, 11117434025], "tags": {"aeroway": "helipad"}}, {"type": "way", "id": 1205346319, "center": {"lat": -12.0857988, "lon": -76.9922011}, "nodes": [11170718954, 11170718953, 11170718952, 11170718951, 11170718950, 11170718949, 11170718948, 11170718947, 11170718946, 11170718945, 11170718944, 11170718943, 11170718942, 11170718941, 11170718940, 11170718939, 11170718938, 11170718937, 11170694936, 11170694935, 11170694934, 11170694933, 11170694932, 11170718954], "tags": {"aeroway": "helipad"}}, {"type": "way", "id": 1208696355, "center": {"lat": -11.7699819, "lon": -77.1717244}, "nodes": [11199187213, 11199187198, 11199187199, 11199187200, 11199187212, 11199187201, 11199187202, 11199187203, 11199187204, 11199187205, 11199187211, 11199187206, 11199187207, 11199187208, 11199187209, 11199187210, 11199187213], "tags": {"aeroway": "helipad"}}]}