{"version": 0.6, "generator": "Overpass API 0.7.61.5 4133829e", "osm3s": {"timestamp_osm_base": "2023-10-31T20:38:15Z", "copyright": "The data included in this document is from www.openstreetmap.org. The data is made available under ODbL."}, "elements": [{"type": "node", "id": 369071137, "lat": 45.8833767, "lon": -69.2322724, "tags": {"addr:state": "ME", "aeroway": "helipad", "ele": "287", "gnis:county_name": "Piscataquis", "gnis:created": "09/01/1994", "gnis:feature_id": "582133", "gnis:feature_type": "Airport", "name": "Chesuncook Forestry District Heliport", "wikidata": "Q61673182"}}, {"type": "node", "id": 369071385, "lat": 44.2831321, "lon": -69.2386542, "tags": {"addr:state": "ME", "aeroway": "helipad", "ele": "76", "gnis:county_name": "Knox", "gnis:created": "09/01/1994", "gnis:feature_id": "582107", "gnis:feature_type": "Airport", "name": "Ben Hur Heliport", "wikidata": "Q61673145"}}, {"type": "node", "id": 369071509, "lat": 43.8983612, "lon": -69.9796858, "tags": {"FIXME": "where the hell is this thing", "addr:state": "ME", "aeroway": "helipad", "ele": "24", "gnis:county_name": "Cumberland", "gnis:created": "09/01/1994", "gnis:feature_id": "582123", "gnis:feature_type": "Airport", "name": "Memorial Hospital Heliport"}}, {"type": "node", "id": 369072196, "lat": 45.8992182, "lon": -68.4366962, "tags": {"addr:state": "ME", "aeroway": "helipad", "ele": "149", "gnis:county_name": "Penobscot", "gnis:created": "09/01/1994", "gnis:feature_id": "582231", "gnis:feature_type": "Airport", "name": "Wheelabrator-Sherman Heliport"}}, {"type": "node", "id": 369072248, "lat": 45.5695113, "lon": -67.4274987, "tags": {"addr:state": "ME", "aeroway": "helipad", "ele": "116", "gnis:county_name": "Washington", "gnis:created": "09/01/1994", "gnis:feature_id": "582240", "gnis:feature_type": "Airport", "name": "Vanceboro Heliport"}}, {"type": "node", "id": 369072465, "lat": 45.8833709, "lon": -69.9822878, "tags": {"addr:state": "ME", "aeroway": "helipad", "ele": "373", "fixme": "Please check and confirm position", "gnis:county_name": "Somerset", "gnis:created": "09/01/1994", "gnis:feature_id": "582209", "gnis:feature_type": "Airport", "name": "Seboomook Forestry District Headquarters Heliport", "wikidata": "Q61673291"}}, {"type": "node", "id": 369072470, "lat": 44.7833976, "lon": -69.3722703, "tags": {"addr:state": "ME", "aeroway": "helipad", "ele": "72", "gnis:county_name": "Somerset", "gnis:created": "09/01/1994", "gnis:feature_id": "582208", "gnis:feature_type": "Airport", "name": "Cianbro Heliport"}}, {"type": "node", "id": 369072704, "lat": 44.540171, "lon": -67.8838874, "tags": {"addr:state": "ME", "aeroway": "helipad", "ele": "13", "gnis:county_name": "Washington", "gnis:created": "09/01/1994", "gnis:feature_id": "582183", "gnis:feature_type": "Airport", "name": "Milbridge Heliport", "wikidata": "Q61673258"}}, {"type": "node", "id": 369072952, "lat": 43.8964693, "lon": -69.9803278, "tags": {"addr:state": "ME", "aeroway": "helipad", "ele": "25", "gnis:county_name": "Cumberland", "gnis:created": "05/08/2001", "gnis:feature_id": "1912624", "gnis:feature_type": "Airport", "name": "Kiwanis Helipad", "wikidata": "Q35271177"}}, {"type": "node", "id": 850025937, "lat": 44.6344503, "lon": -63.5031431, "tags": {"aeroway": "helipad", "source": "CanVec 6.0 - NRCan"}}, {"type": "node", "id": 850026518, "lat": 44.6336759, "lon": -63.5031386, "tags": {"aeroway": "helipad", "source": "CanVec 6.0 - NRCan"}}, {"type": "node", "id": 850027009, "lat": 44.6328937, "lon": -63.5031399, "tags": {"aeroway": "helipad", "source": "CanVec 6.0 - NRCan"}}, {"type": "node", "id": 862340803, "lat": 49.1360037, "lon": -68.2010597, "tags": {"aeroway": "helipad"}}, {"type": "node", "id": 981200947, "lat": 45.0931574, "lon": -63.3969311, "tags": {"aeroway": "helipad", "name": "Shubenacadie Helipad", "operator": "Province of Nova Scotia"}}, {"type": "node", "id": 1042134097, "lat": 45.812174, "lon": -64.2201656, "tags": {"aeroway": "helipad", "name": "Amherst Heliport", "source": "ourairports.com"}}, {"type": "node", "id": 1042134100, "lat": 46.417803, "lon": -63.7739628, "tags": {"aeroway": "helipad", "name": "Summerside (Prince County Hospital) Heliport", "source": "ourairports.com", "surface": "asphalt", "tc": "CCH6"}}, {"type": "node", "id": 1042134126, "lat": 44.645941, "lon": -63.586531, "tags": {"aeroway": "helipad", "icao": "CHQE", "name": "Halifax (Queen Elzabeth II Health Sciences Centre) Heliport", "ref": "CHQE", "source": "ourairports.com"}}, {"type": "node", "id": 1042134130, "lat": 44.636994, "lon": -63.58442, "tags": {"addr:city": "Halifax", "addr:district": "7", "addr:housenumber": "5980", "addr:postcode": "B3K 6R8", "addr:province": "Nova Scotia", "addr:street": "South Street", "aeroway": "helipad", "icao": "CIW2", "name": "Halifax (IWK Health Centre) Heliport", "ref": "CIW2", "source": "ourairports.com"}}, {"type": "node", "id": 1042134135, "lat": 45.0817152, "lon": -64.5000371, "tags": {"aeroway": "helipad", "name": "Kentville (Valley Regional Hospital) Heliport"}}, {"type": "node", "id": 1042144532, "lat": 43.7502922, "lon": -65.3096851, "tags": {"aeroway": "helipad", "name": "Shelburne (Roseway Hospital) Heliport", "source": "ourairports.com"}}, {"type": "node", "id": 1042144604, "lat": 46.0490132, "lon": -65.0620328, "tags": {"aeroway": "helipad", "name": "Moncton / Salisbury Heliport", "operator": "Irving Oil", "source": "ourairports.com", "surface": "asphalt", "tc": "CDB5"}}, {"type": "node", "id": 1042144656, "lat": 45.5114446, "lon": -61.0330439, "tags": {"aeroway": "helipad", "name": "Arichat (St. Anne Ladies Auxiliary Hospital) Heliport", "source": "ourairports.com"}}, {"type": "node", "id": 1042144741, "lat": 45.0940062, "lon": -64.5095676, "tags": {"aeroway": "helipad", "name": "Kentville (Camp Aldershot) Heliport", "source": "ourairports.com"}}, {"type": "node", "id": 1042144889, "lat": 44.0384794, "lon": -64.7052614, "tags": {"aeroway": "helipad", "name": "Liverpool (Queens General Hospital) Heliport", "source": "ourairports.com"}}, {"type": "node", "id": 1042145049, "lat": 46.1993948, "lon": -61.291567, "tags": {"aeroway": "helipad", "name": "Inverness (Consolidated Memorial Hospital) Heliport", "source": "ourairports.com"}}, {"type": "node", "id": 1042145330, "lat": 49.1990799, "lon": -68.2851873, "tags": {"aeroway": "helipad", "name": "H\u00e9liport, Baie-Comeau / H\u00e9li-Manicouagan", "name:en": "Baie-Comeau / H\u00e9li-Manicouagan Heliport", "source": "ourairports.com"}}, {"type": "node", "id": 1042145353, "lat": 47.8490083, "lon": -69.5422488, "tags": {"aeroway": "helipad", "name": "H\u00e9liport, Rivi\u00e8re-du-Loup", "name:en": "Rivi\u00e8re-du-Loup Heliport", "source": "ourairports.com"}}, {"type": "node", "id": 1042145417, "lat": 44.6574469, "lon": -63.6117424, "tags": {"aeroway": "helipad", "name": "Halifax (Windsor Park) Heliport", "source": "ourairports.com"}}, {"type": "node", "id": 1042149570, "lat": 43.8585014, "lon": -69.884201, "tags": {"aeroway": "helipad", "name": "Miara Heliport", "source": "ourairports.com", "wikidata": "Q61673331"}}, {"type": "node", "id": 1849833518, "lat": 44.3399625, "lon": -68.0608266, "tags": {"aeroway": "helipad"}}, {"type": "node", "id": 1917968453, "lat": 45.5133791, "lon": -61.2530261, "tags": {"aeroway": "helipad", "source": "NRCan-CanVec-10.0"}}, {"type": "node", "id": 2134364753, "lat": 45.7378288, "lon": -66.2196904, "tags": {"aeroway": "helipad", "source": "Bing"}}, {"type": "node", "id": 2406497129, "lat": 45.6083311, "lon": -61.9702109, "tags": {"aeroway": "helipad", "name": "DNR Helipad"}}, {"type": "node", "id": 3605818499, "lat": 44.6406778, "lon": -63.5032145, "tags": {"aeroway": "helipad"}}, {"type": "node", "id": 3605818537, "lat": 44.6390136, "lon": -63.5131172, "tags": {"aeroway": "helipad"}}, {"type": "node", "id": 3605818564, "lat": 44.6388838, "lon": -63.5150484, "tags": {"aeroway": "helipad"}}, {"type": "node", "id": 3940413240, "lat": 45.3496981, "lon": -63.3054164, "tags": {"aeroway": "helipad"}}, {"type": "node", "id": 4396167152, "lat": 45.8151041, "lon": -68.8886376, "tags": {"aeroway": "helipad"}}, {"type": "node", "id": 4409984366, "lat": 45.147859, "lon": -63.4499404, "tags": {"aeroway": "helipad"}}, {"type": "node", "id": 4678645405, "lat": 45.147215, "lon": -61.9820309, "tags": {"aeroway": "helipad"}}, {"type": "node", "id": 5859932737, "lat": 45.185022, "lon": -61.9838418, "tags": {"aeroway": "helipad"}}, {"type": "node", "id": 6286442640, "lat": 45.8720027, "lon": -66.5313005, "tags": {"aeroway": "helipad"}}, {"type": "node", "id": 6286442641, "lat": 45.8718697, "lon": -66.531081, "tags": {"aeroway": "helipad"}}, {"type": "node", "id": 6775422185, "lat": 44.3828788, "lon": -64.327995, "tags": {"aeroway": "helipad"}}, {"type": "node", "id": 6935876950, "lat": 45.2898441, "lon": -66.0163141, "tags": {"aeroway": "helipad"}}, {"type": "node", "id": 7175680382, "lat": 43.764341, "lon": -69.3145009, "tags": {"addr:city": "Monhegan", "addr:housenumber": "105", "addr:postcode": "04852", "addr:state": "ME", "addr:street": "Lighthouse Hill Road", "aeroway": "helipad", "faa": "ME78", "lit": "call_ahead", "name": "Lighthouse Hill Road", "surface": "grass", "wikidata": "Q74843878"}}, {"type": "node", "id": 7881772545, "lat": 41.9059514, "lon": -69.9774228, "tags": {"aeroway": "helipad", "surface": "asphalt"}}, {"type": "node", "id": 8026623087, "lat": 44.3054168, "lon": -68.9119264, "tags": {"aeroway": "helipad", "lit": "no", "ref": "H1", "surface": "asphalt"}}, {"type": "node", "id": 8026623093, "lat": 44.1716271, "lon": -68.6833215, "tags": {"aeroway": "helipad", "ref": "H1", "surface": "asphalt"}}, {"type": "node", "id": 8026623094, "lat": 44.1652166, "lon": -68.4302517, "tags": {"aeroway": "helipad", "ref": "H1", "surface": "concrete"}}, {"type": "node", "id": 9202678251, "lat": 48.8308131, "lon": -66.7078665, "tags": {"aeroway": "helipad", "name": "H\u00e9liport"}}, {"type": "node", "id": 9329833406, "lat": 48.9737528, "lon": -65.4418331, "tags": {"aeroway": "helipad", "name": "H4"}}, {"type": "node", "id": 9329833407, "lat": 48.9763468, "lon": -65.444173, "tags": {"aeroway": "helipad", "name": "H3"}}, {"type": "node", "id": 9329833408, "lat": 48.9820304, "lon": -65.4536124, "tags": {"aeroway": "helipad", "name": "H2"}}, {"type": "node", "id": 9329833411, "lat": 48.9798136, "lon": -65.4386717, "tags": {"aeroway": "helipad", "name": "H5"}}, {"type": "node", "id": 9329833412, "lat": 48.9853566, "lon": -65.4455842, "tags": {"aeroway": "helipad", "name": "H7"}}, {"type": "node", "id": 9329833413, "lat": 48.9864819, "lon": -65.4474403, "tags": {"aeroway": "helipad", "name": "H8"}}, {"type": "node", "id": 9374901887, "lat": 44.8758729, "lon": -63.5224985, "tags": {"aeroway": "heliport", "name": "Canadian Helicopters"}}, {"type": "node", "id": 9374901888, "lat": 44.8768618, "lon": -63.5213292, "tags": {"aeroway": "heliport", "name": "EHS Life Flight"}}, {"type": "node", "id": 9374901891, "lat": 44.8725642, "lon": -63.5298479, "tags": {"addr:city": "Goffs", "addr:housenumber": "95", "addr:postcode": "B2T 1K3", "addr:province": "Nova Scotia", "addr:street": "Baldwin Drive", "aeroway": "heliport", "name": "Cougar Helicopter"}}, {"type": "node", "id": 9546589567, "lat": 44.6571224, "lon": -65.6325645, "tags": {"aeroway": "helipad"}}, {"type": "node", "id": 9824254062, "lat": 46.8505502, "lon": -68.9379312, "tags": {"aeroway": "helipad"}}, {"type": "node", "id": 9854964441, "lat": 46.1441476, "lon": -60.2028518, "tags": {"aeroway": "helipad"}}, {"type": "node", "id": 10076393968, "lat": 45.8564365, "lon": -63.658292, "tags": {"aeroway": "helipad"}}, {"type": "node", "id": 11278355100, "lat": 45.2804146, "lon": -66.0415837, "tags": {"access": "private", "aeroway": "helipad"}}, {"type": "way", "id": 28330984, "center": {"lat": 46.2554594, "lon": -63.0988886}, "nodes": [311123226, 1693633933, 1693633804, 1693633692, 1693633813, 311123227, 1693633741, 1693633736, 1693633762, 311123228, 1693633707, 1693633719, 1693633915, 311123229, 1693633787, 2623730120, 1693633914, 1693633823, 1693633908, 311123226], "tags": {"aeroway": "helipad", "name": "Charlottetown (Queen Elizabeth Hospital) Heliport", "surface": "asphalt", "tc": "CDV3"}}, {"type": "way", "id": 71358030, "center": {"lat": 44.6254363, "lon": -63.5633688}, "nodes": [849047788, 849047790, 849047789, 8744063547, 9241877718, 8744063543, 849047788], "tags": {"aeroway": "helipad", "name": "Halifax (South End) Heliport", "operator": "Port of Halifax"}}, {"type": "way", "id": 72660202, "center": {"lat": 49.1380202, "lon": -68.1950076}, "nodes": [862806619, 862806529, 862806557, 862806602, 862806619], "tags": {"aeroway": "helipad", "barrier": "fence"}}, {"type": "way", "id": 85066852, "center": {"lat": 45.9317382, "lon": -66.6666747}, "nodes": [986974085, 986973849, 986974058, 986973807, 986974085], "tags": {"aeroway": "helipad", "name": "Fredericton (RCMP) Heliport", "operator": "RCMP", "surface": "asphalt", "tc": "CRC2"}}, {"type": "way", "id": 123685246, "center": {"lat": 46.1057713, "lon": -64.6618385}, "nodes": [1378350059, 1378350251, 1378350565, 1378350028, 1378350059], "tags": {"aeroway": "helipad"}}, {"type": "way", "id": 134558556, "center": {"lat": 45.3022574, "lon": -66.0879408}, "nodes": [1479237428, 1479237394, 1479237439, 1479237436, 1479237438, 1479237428], "tags": {"aeroway": "helipad", "name": "Saint John (Regional Hospital) Heliport", "surface": "asphalt", "tc": "CSN6"}}, {"type": "way", "id": 136939648, "center": {"lat": 45.9212819, "lon": -66.6343707}, "nodes": [1502267493, 1502267492, 1502267494, 1502267495, 1502267493], "tags": {"aeroway": "helipad", "name": "Sunbury Helipad", "source": "Bing"}}, {"type": "way", "id": 177335068, "center": {"lat": 44.1425414, "lon": -68.2465965}, "nodes": [1877847267, 1877847269, 1877847265, 1877847263, 1877847267], "tags": {"aeroway": "helipad"}}, {"type": "way", "id": 186333090, "center": {"lat": 45.3330393, "lon": -60.9818455}, "nodes": [1970050571, 1970050577, 1970050583, 1970050598, 1970050600, 1970050602, 1970050607, 1970050610, 1970050613, 1970050620, 1970050625, 1970050644, 1970050646, 1970050650, 1970050653, 1970050654, 1970050655, 1970050652, 1970050651, 1970050648, 1970050630, 1970050622, 1970050617, 1970050614, 1970050611, 1970050608, 1970050605, 1970050604, 1970050601, 1970050599, 1970050585, 1970050581, 1970050574, 1970050567, 1970050561, 1970050551, 1970050544, 1970050541, 1970050538, 1970050533, 1970050536, 1970050539, 1970050542, 1970050548, 1970050555, 1970050557, 1970050563, 1970050571], "tags": {"aeroway": "helipad", "name": "Canso (Eastern Memorial Hospital) Heliport", "source": "ourairports.com", "surface": "paved"}}, {"type": "way", "id": 188973572, "center": {"lat": 44.0385005, "lon": -64.7052375}, "nodes": [1996121503, 1996121485, 1996121493, 1996121463, 1996121476, 1996121382, 1996121448, 1996121361, 1996121405, 1996121477, 1996121452, 1996121428, 1996121482, 1996121459, 1996121351, 1996121378, 1996121469, 7646604303, 1996121454, 1996121503], "tags": {"aeroway": "helipad"}}, {"type": "way", "id": 191052193, "center": {"lat": 45.1690806, "lon": -61.6264197}, "nodes": [2016375682, 2016375678, 2016375684, 2016375680, 2016375682], "tags": {"aeroway": "helipad"}}, {"type": "way", "id": 193368222, "center": {"lat": 45.2391493, "lon": -66.0535956}, "nodes": [2038738264, 2038738263, 2038738266, 2038738267, 2284236980, 2038738264], "tags": {"aeroway": "helipad"}}, {"type": "way", "id": 197978686, "center": {"lat": 45.5534948, "lon": -62.7024612}, "nodes": [2081701620, 2081701779, 6443184810, 6443184811, 2453658620, 2453658429, 2081701620], "tags": {"aeroway": "helipad", "name": "Westville Community Helipad"}}, {"type": "way", "id": 198756629, "center": {"lat": 44.5016742, "lon": -67.101365}, "nodes": [2088551528, 2088551392, 2088551431, 2088551532, 2088551412, 2088551346, 2088551528], "tags": {"aeroway": "helipad"}}, {"type": "way", "id": 205879703, "center": {"lat": 45.6532615, "lon": -68.7169801}, "nodes": [2158644541, 2158644545, 2158644544, 2158644540, 2158644541], "tags": {"aeroway": "helipad"}}, {"type": "way", "id": 223416273, "center": {"lat": 45.8378539, "lon": -66.436651}, "nodes": [1896959002, 2323140062, 1896960413, 2323140061, 1896958999, 1896959002], "tags": {"aeroway": "helipad", "iata": "YCX", "icao": "CYCX", "landuse": "military", "lit": "no", "name": "CFB Gagetown Heliport", "source": "Bing", "surface": "asphalt"}}, {"type": "way", "id": 237698208, "center": {"lat": 44.6570864, "lon": -65.6326022}, "nodes": [2455810031, 2455810037, 2455906114, 2455884645, 2455810035, 2455810033, 2455810031], "tags": {"aeroway": "helipad", "name": "Parade Square"}}, {"type": "way", "id": 239004227, "center": {"lat": 46.6229599, "lon": -61.0138713}, "nodes": [2468094625, 2468094617, 2468094548, 2468094552, 2468094619, 2468094621, 2468094625], "tags": {"aeroway": "helipad"}}, {"type": "way", "id": 243245963, "center": {"lat": 45.6267987, "lon": -61.9819076}, "nodes": [1042144681, 2506671854, 2506671856, 2506671858, 2506671860, 2506671862, 2506671864, 2506671827, 2506671830, 2506671836, 2506671838, 2506671840, 2506671842, 2506671844, 2506671846, 2506671848, 2506671850, 2506671832, 2506671834, 1042144681], "tags": {"aeroway": "helipad", "name": "Antigonish (St. Martha's Regional Hospital) Heliport", "source": "ourairports.com;Bing"}}, {"type": "way", "id": 259960782, "center": {"lat": 45.8120763, "lon": -64.2202347}, "nodes": [2654186389, 2654186392, 2654186395, 2654186398, 2654186389], "tags": {"addr:city": "Amherst", "addr:housenumber": "12", "addr:postcode": "B4H 4J2", "addr:province": "Nova Scotia", "addr:street": "Chandler Road", "aeroway": "helipad"}}, {"type": "way", "id": 294611825, "center": {"lat": 44.3618129, "lon": -69.7798361}, "nodes": [2982030554, 2982030365, 2982029512, 2982030409, 2982030554], "tags": {"aeroway": "helipad"}}, {"type": "way", "id": 322856414, "center": {"lat": 44.9869423, "lon": -64.1208003}, "nodes": [3296490869, 3296490870, 3296490871, 3296490872, 3296490873, 3296489855, 3296489856, 3296489857, 3296489858, 3296489859, 3296490865, 3296490866, 3296490867, 3296490868, 3296489860, 3296490861, 3296490862, 3296490863, 3296490864, 3296490869], "tags": {"aeroway": "helipad", "is_in:country_code": "CA", "is_in:province": "Nova Scotia"}}, {"type": "way", "id": 325113378, "center": {"lat": 47.9969539, "lon": -69.4312087}, "nodes": [3317804893, 3317804891, 3317804888, 3317804889, 3317804892, 3317804893], "tags": {"aeroway": "helipad"}}, {"type": "way", "id": 325722321, "center": {"lat": 47.3764666, "lon": -68.3120251}, "nodes": [3323396311, 3323396312, 3323396313, 3323396314, 3323396311], "tags": {"aeroway": "helipad"}}, {"type": "way", "id": 330592816, "center": {"lat": 47.366744, "lon": -68.3303894}, "nodes": [3375700784, 3375700785, 3375700786, 3375700787, 3375700784], "tags": {"aeroway": "helipad", "note": "Twin Rivers Paper Company helipad"}}, {"type": "way", "id": 345605003, "center": {"lat": 43.8961484, "lon": -69.9678164}, "nodes": [3522475397, 3522475400, 3522475401, 3522475398, 3522475397], "tags": {"aeroway": "helipad"}}, {"type": "way", "id": 361072759, "center": {"lat": 46.1344546, "lon": -67.8431343}, "nodes": [3655948954, 3655948955, 3655948956, 3655948957, 3655948954], "tags": {"aeroway": "helipad"}}, {"type": "way", "id": 361916503, "center": {"lat": 45.0385628, "lon": -66.891488}, "nodes": [3663218370, 3663218371, 3663218372, 3663218373, 3663218370], "tags": {"aeroway": "helipad"}}, {"type": "way", "id": 368345420, "center": {"lat": 44.5690965, "lon": -67.3667035}, "nodes": [3721890483, 3721890481, 3721890480, 3721890482, 3721890483], "tags": {"aeroway": "helipad"}}, {"type": "way", "id": 388084064, "center": {"lat": 44.1431426, "lon": -69.0853954}, "nodes": [3912840512, 3912840513, 3912840514, 3912840515, 3912840512], "tags": {"aeroway": "helipad", "faa": "ME76", "gnis:feature_id": "582222", "name": "Penobscot Bay Medical Center Heliport", "surface": "asphalt", "wikidata": "Q61673301"}}, {"type": "way", "id": 401902481, "center": {"lat": 44.0132184, "lon": -69.9024062}, "nodes": [4043138809, 4043138810, 4043138811, 4043138812, 4043138809], "tags": {"addr:city": "Bowdoinham", "addr:postcode": "04008", "addr:state": "ME", "addr:street": "Center Street", "aeroway": "helipad", "operator": "Bowdoinham Fire & EMS"}}, {"type": "way", "id": 414251095, "center": {"lat": 44.7577248, "lon": -69.7143893}, "nodes": [4154214541, 4154214542, 4154214543, 4154214544, 4154214541], "tags": {"aeroway": "helipad"}}, {"type": "way", "id": 431446820, "center": {"lat": 44.5662114, "lon": -69.6478644}, "nodes": [4306425463, 4306425427, 4306425474, 4306425469, 4306425463], "tags": {"aeroway": "helipad", "source": "Esri 2019"}}, {"type": "way", "id": 441954917, "center": {"lat": 45.485145, "lon": -69.7105192}, "nodes": [4396413070, 4396413069, 4396413067, 4396413068, 4396413070], "tags": {"aeroway": "helipad", "building": "yes"}}, {"type": "way", "id": 443044200, "center": {"lat": 44.8082217, "lon": -68.7520463}, "nodes": [369071292, 4406873743, 4387299868, 4406873745, 369071292], "tags": {"aeroway": "helipad", "faa": "ME02", "gnis:feature_id": "582112", "name": "Eastern Maine Medical Center Heliport", "rooftop": "yes", "surface": "concrete", "wikidata": "Q61673153"}}, {"type": "way", "id": 443072377, "center": {"lat": 46.6758799, "lon": -67.9989615}, "nodes": [4407100257, 4407100253, 4407100252, 1974729517, 4407100257], "tags": {"aeroway": "helipad"}}, {"type": "way", "id": 443089281, "center": {"lat": 45.1771335, "lon": -67.2679299}, "nodes": [4407254884, 4407254882, 4407254885, 4407254888, 4407254884], "tags": {"aeroway": "helipad"}}, {"type": "way", "id": 443091866, "center": {"lat": 44.7134417, "lon": -67.4758967}, "nodes": [4407285453, 4407285450, 4407285451, 4407285455, 4407285453], "tags": {"aeroway": "helipad"}}, {"type": "way", "id": 443190987, "center": {"lat": 44.5465559, "lon": -68.4174094}, "nodes": [4408132541, 4408132542, 4408132552, 4408132547, 4408132541], "tags": {"aeroway": "helipad", "source": "Esri 2019"}}, {"type": "way", "id": 443225642, "center": {"lat": 43.8506374, "lon": -69.6380058}, "nodes": [4408427683, 4408427684, 10575593129, 10575593127, 10575593139, 10575593128, 4408427682, 10575593131, 10575593132, 10575593130, 4408427681, 10594530261, 4408427683], "tags": {"aeroway": "helipad"}}, {"type": "way", "id": 443244512, "center": {"lat": 44.5421351, "lon": -69.6612454}, "nodes": [4408591795, 4408591794, 4408591796, 4408591797, 4408591795], "tags": {"aeroway": "helipad"}}, {"type": "way", "id": 455599653, "center": {"lat": 44.6404314, "lon": -63.5602107}, "nodes": [4519869586, 4519869587, 4519869588, 4519869689, 4519869690, 4519869691, 4519869586], "tags": {"addr:city": "Halifax", "addr:province": "Nova Scotia", "addr:street": "Georges Island Road", "aeroway": "helipad", "description": "Transport Canada"}}, {"type": "way", "id": 457879149, "center": {"lat": 44.8051683, "lon": -68.8163345}, "nodes": [4539422400, 4539422401, 4539422402, 4539422403, 4539422400], "tags": {"aeroway": "helipad"}}, {"type": "way", "id": 472809541, "center": {"lat": 44.7537358, "lon": -65.5125029}, "nodes": [5802704930, 4670131535, 5802704917, 5802704918, 5802704919, 5802704920, 4670131536, 4670131537, 4670131538, 5802704921, 5802704922, 5802704923, 5802704924, 5802704925, 5802704926, 5802704927, 5802704928, 5802704929, 5648325941, 5802704930], "tags": {"addr:city": "Annapolis Royal", "addr:housenumber": "236", "addr:postcode": "B0S 1E0", "addr:province": "Nova Scotia", "addr:street": "Prince Albert Road", "aeroway": "helipad", "name": "Annapolis Tidal Generating Station Helipad", "ref": "WMR3DM"}}, {"type": "way", "id": 515028499, "center": {"lat": 44.7637338, "lon": -66.73306}, "nodes": [5030618712, 5030618713, 5030618714, 5030618715, 5030618712], "tags": {"aeroway": "helipad"}}, {"type": "way", "id": 518063859, "center": {"lat": 43.7829823, "lon": -68.8554504}, "nodes": [5054400158, 5054400155, 5054400156, 5054400157, 5054400158], "tags": {"aeroway": "helipad", "image": "https://marinas.com/view/lighthouse/ypa54_Matinicus_Island_LIghthouse_ME_United_States#&gid=1&pid=1", "surface": "wood"}}, {"type": "way", "id": 519748528, "center": {"lat": 45.572249, "lon": -62.6442829}, "nodes": [5067458691, 5067458692, 5067458693, 5067458694, 5067458691], "tags": {"aeroway": "helipad", "name": "New Glasgow (Aberdeen Hospital) Heliport (CNG2)"}}, {"type": "way", "id": 546854836, "center": {"lat": 45.1713134, "lon": -69.8633768}, "nodes": [5284240046, 5284240047, 5284240048, 5284240049, 5284240046], "tags": {"aeroway": "helipad", "area": "yes"}}, {"type": "way", "id": 547089056, "center": {"lat": 45.4584201, "lon": -69.6112105}, "nodes": [5286247010, 5286247011, 5286247012, 5286247013, 5286247010], "tags": {"aeroway": "helipad", "source": "Bing"}}, {"type": "way", "id": 549837494, "center": {"lat": 44.7824453, "lon": -63.1585268}, "nodes": [5311405323, 5311405324, 5311405325, 5311405326, 5311405323], "tags": {"addr:city": "Musquodoboit Harbour", "addr:housenumber": "7704", "addr:postcode": "B0J 2L0", "addr:province": "Nova Scotia", "addr:street": "Highway 7", "aeroway": "helipad", "name": "Twin Oaks EHS Helipad"}}, {"type": "way", "id": 551500297, "center": {"lat": 44.9462231, "lon": -65.0588153}, "nodes": [5326062877, 5326062878, 5326062879, 5326062880, 5326062881, 5326062882, 5326062883, 5326062865, 5326062866, 5326062869, 5326062870, 5326062871, 5326062872, 5326062873, 5326062874, 5326062875, 5326062876, 5326062867, 5326062868, 5326062877], "tags": {"aeroway": "helipad", "is_in:country_code": "CA", "is_in:province": "Nova Scotia"}}, {"type": "way", "id": 564847658, "center": {"lat": 45.0807544, "lon": -67.0534636}, "nodes": [5441367635, 5441367636, 5441367637, 5441367638, 5441367639, 5441367640, 5441367641, 5441367623, 5441367624, 5441367627, 5441367628, 5441367629, 5441367630, 5441367631, 5441367632, 5441367633, 5441367634, 5441367625, 5441367626, 5441367635], "tags": {"aeroway": "helipad"}}, {"type": "way", "id": 574644336, "center": {"lat": 44.8226697, "lon": -62.5985953}, "nodes": [5515461950, 5515461951, 5515461952, 5515461953, 5515461950], "tags": {"aeroway": "helipad"}}, {"type": "way", "id": 582260508, "center": {"lat": 45.1885802, "lon": -69.2367679}, "nodes": [3057103511, 5569133408, 5569133407, 5569133406, 3057103511], "tags": {"aeroway": "helipad", "faa": "ME43", "name": "Mayo Regional Hospital Heliport", "surface": "asphalt", "wikidata": "Q61673193"}}, {"type": "way", "id": 586366243, "center": {"lat": 44.4132897, "lon": -68.9940729}, "nodes": [5602513812, 5602513811, 5602513810, 5602513809, 5602513812], "tags": {"aeroway": "helipad", "faa": "98ME", "name": "Waldo County General Hospital Heliport", "surface": "asphalt", "wikidata": "Q61673157"}}, {"type": "way", "id": 586372083, "center": {"lat": 44.7895959, "lon": -69.3702061}, "nodes": [5602573258, 5602573257, 5602573256, 5602573255, 5602573258], "tags": {"aeroway": "helipad", "name": "Sebasticook Valley Health Heliport", "source": "Esri 2018"}}, {"type": "way", "id": 587069573, "center": {"lat": 45.0404964, "lon": -63.1409621}, "nodes": [5608354335, 5608354336, 5608354337, 5608354338, 5608354335], "tags": {"addr:city": "Middle Musquodoboit", "addr:housenumber": "492", "addr:postcode": "B0N 1X0", "addr:province": "Nova Scotia", "addr:street": "Archibald Brook Road", "aeroway": "helipad", "name": "EHS LifeFlight"}}, {"type": "way", "id": 611315933, "center": {"lat": 44.2030733, "lon": -69.6075508}, "nodes": [1042149566, 5788101684, 5788101683, 5788101682, 1042149566], "tags": {"addr:city": "Whitefield", "addr:housenumber": "55", "addr:postcode": "04353", "addr:state": "ME", "addr:street": "Town Farm Lane", "aeroway": "helipad", "building": "yes", "name": "Maine Helicopters Heliport", "source": "ourairports.com", "wikidata": "Q61673274"}}, {"type": "way", "id": 647860006, "center": {"lat": 45.8032233, "lon": -64.1965757}, "nodes": [6083446034, 6083446032, 6083446031, 6083446033, 6083446034], "tags": {"aeroway": "helipad"}}, {"type": "way", "id": 660565453, "center": {"lat": 45.0817172, "lon": -64.5000486}, "nodes": [6184597307, 6184597297, 6184597306, 6184597301, 6184597298, 6184597312, 6184597303, 6184597310, 6184597302, 6184597304, 6184597305, 6184597300, 6184597308, 6184597309, 6184597311, 6184597299, 6184597313, 6184597307], "tags": {"aeroway": "helipad"}}, {"type": "way", "id": 664501624, "center": {"lat": 43.9329434, "lon": -60.0055105}, "nodes": [6219474858, 6219474859, 4051488412, 6219474860, 6219474861, 6219474862, 6219474863, 6219474864, 1042134251, 6219466086, 6219474850, 6219474851, 6219474852, 6219474853, 4051488413, 6219474854, 6219474855, 6219474856, 6219474857, 6219459684, 6219466085, 6219474858], "tags": {"aeroway": "helipad", "name": "Sable Island Heliport", "source": "ourairports.com"}}, {"type": "way", "id": 669007485, "center": {"lat": 44.7903512, "lon": -67.7692695}, "nodes": [6264780158, 6264780159, 6264780160, 6264780161, 6264780158], "tags": {"aeroway": "helipad"}}, {"type": "way", "id": 683520336, "center": {"lat": 46.2976163, "lon": -63.1196922}, "nodes": [6402185351, 6402185352, 6402185353, 6402185354, 6402185355, 6402185356, 6402185357, 6402185358, 6402185359, 6402185360, 6402185351], "tags": {"aeroway": "helipad", "source": "Bing"}}, {"type": "way", "id": 734919605, "center": {"lat": 43.9049543, "lon": -69.8911614}, "nodes": [1042149558, 6883084400, 6883084401, 6883084402, 6883084403, 6883084404, 6883084405, 6883084406, 6883084415, 6883084416, 6883084417, 6883084407, 6883084408, 6883084409, 6883084410, 6883084411, 6883084412, 6883084413, 6883084414, 1042149558], "tags": {"aeroway": "helipad", "name": "Mid Coast Hospital Heliport", "source": "ourairports.com", "wikidata": "Q61673174"}}, {"type": "way", "id": 745966434, "center": {"lat": 45.349683, "lon": -63.3054131}, "nodes": [6981312609, 6981312610, 6981312592, 6981312593, 6981312594, 6981312595, 6981312596, 6981312597, 6981312598, 6981312606, 6981312607, 6981312608, 6981312599, 6981312600, 6981312601, 6981312602, 6981312603, 6981312604, 6981312605, 6981312609], "tags": {"aeroway": "helipad"}}, {"type": "way", "id": 756877658, "center": {"lat": 45.3487056, "lon": -68.5166145}, "nodes": [7069193179, 7069193180, 7069193181, 7069193182, 7069193179], "tags": {"aeroway": "helipad"}}, {"type": "way", "id": 758268169, "center": {"lat": 44.6073073, "lon": -63.6753109}, "nodes": [7081540282, 7081540283, 7081540284, 7081550485, 7081550486, 7081550487, 7081550488, 7081540282], "tags": {"aeroway": "helipad", "surface": "asphalt"}}, {"type": "way", "id": 758735461, "center": {"lat": 45.4027574, "lon": -61.5064322}, "nodes": [7086353712, 7086353713, 7086353714, 7086353715, 7086353716, 7086353717, 7086353718, 7086353719, 7086353720, 7086353721, 7086353722, 7086353704, 7086353707, 7086353708, 7086353709, 7086353710, 7086353711, 7086353705, 7086353706, 7086353712], "tags": {"aeroway": "helipad"}}, {"type": "way", "id": 789332430, "center": {"lat": 44.5276726, "lon": -67.6166456}, "nodes": [7380458330, 7380458327, 7380458328, 7380458329, 7380458330], "tags": {"aeroway": "helipad", "name": "U.S. Coast Guard - Station Jonesport", "operator": "U.S. Coast Guard - Station Jonesport"}}, {"type": "way", "id": 835812667, "center": {"lat": 47.2648742, "lon": -68.5931938}, "nodes": [7801419940, 7801419941, 9886184384, 7801419942, 7801419943, 7801419940], "tags": {"aeroway": "helipad", "source": "Bing"}}, {"type": "way", "id": 835814519, "center": {"lat": 45.9398691, "lon": -66.6546649}, "nodes": [7801431993, 7801431994, 7801431995, 7801431996, 7801431993], "tags": {"aeroway": "helipad", "source": "Esri 2015"}}, {"type": "way", "id": 835815580, "center": {"lat": 44.6159894, "lon": -65.7620431}, "nodes": [1042144626, 7801447472, 7801447473, 7801447474, 7801447475, 7801447476, 7801447477, 7801447478, 7801447479, 7801456589, 7801447480, 7801447481, 7801447482, 7801447483, 7801447484, 7801456585, 7801456586, 7801456587, 7801456588, 1042144626], "tags": {"aeroway": "helipad", "name": "Digby (General Hospital) Heliport", "source": "ourairports.com;Bing"}}, {"type": "way", "id": 835816729, "center": {"lat": 44.3821281, "lon": -64.5104712}, "nodes": [1042144665, 7801464041, 7801464042, 7801464043, 7801464044, 7801464045, 7801464046, 7801464047, 7801464048, 7801464058, 7801464049, 7801464050, 7801464051, 7801464052, 7801464053, 7801464054, 7801464055, 7801464056, 7801464057, 1042144665], "tags": {"aeroway": "helipad", "name": "Bridgewater (South Shore Regional Hospital) Heliport", "source": "ourairports.com;Bing"}}, {"type": "way", "id": 835825230, "center": {"lat": 44.4119628, "lon": -68.5880419}, "nodes": [7801467676, 7801467677, 7801467678, 7801467679, 7801467676], "tags": {"aeroway": "helipad", "source": "Esri 2018"}}, {"type": "way", "id": 835827489, "center": {"lat": 44.0266577, "lon": -69.5301093}, "nodes": [7801505714, 7801505715, 7801505716, 7801505717, 7801505714], "tags": {"aeroway": "helipad", "source": "Esri 2019"}}, {"type": "way", "id": 835829560, "center": {"lat": 44.2752739, "lon": -69.7048798}, "nodes": [7801548507, 7801548508, 7801548509, 7801548510, 7801548507], "tags": {"aeroway": "helipad", "source": "Esri 2019"}}, {"type": "way", "id": 881300847, "center": {"lat": 47.9107637, "lon": -69.8065961}, "nodes": [8196661038, 8196661039, 8196661040, 8196661041, 8196661038], "tags": {"aeroway": "helipad"}}, {"type": "way", "id": 890968468, "center": {"lat": 43.8483523, "lon": -66.1212671}, "nodes": [8280787790, 8280787791, 8280787792, 8280787793, 8280787790], "tags": {"aeroway": "helipad", "name": "Yarmouth (Regional Hospital) Heliport"}}, {"type": "way", "id": 970796260, "center": {"lat": 44.7995508, "lon": -66.7851141}, "nodes": [8984690459, 8984690460, 8984690461, 8984690462, 8984690459], "tags": {"aeroway": "helipad", "lit": "no", "surface": "wood"}}, {"type": "way", "id": 992362618, "center": {"lat": 43.7502746, "lon": -65.3096926}, "nodes": [9168689844, 9168689837, 9170870576, 9170870577, 9168689844], "tags": {"aeroway": "helipad", "surface": "asphalt"}}, {"type": "way", "id": 998470056, "center": {"lat": 44.8104591, "lon": -68.8116337}, "nodes": [9219141194, 9219141195, 9219141196, 9219141197, 9219141194], "tags": {"aeroway": "helipad"}}, {"type": "way", "id": 1005711310, "center": {"lat": 43.8982074, "lon": -69.9355135}, "nodes": [9279180668, 9279180669, 9279180670, 9279180671, 9279180668], "tags": {"aeroway": "helipad"}}, {"type": "way", "id": 1087685367, "center": {"lat": 45.3296196, "lon": -65.8945146}, "nodes": [9965628350, 9965628332, 9965628349, 9965628348, 9965628347, 9965628350], "tags": {"aeroway": "helipad", "surface": "concrete"}}, {"type": "way", "id": 1104544364, "center": {"lat": 43.7079267, "lon": -69.758048}, "nodes": [7481903287, 10107451603, 10107467863, 10107467820, 7481903287], "tags": {"aeroway": "helipad"}}, {"type": "way", "id": 1112137758, "center": {"lat": 43.7794065, "lon": -69.6503936}, "nodes": [10174568251, 10174568252, 10174568253, 10174568254, 10174568255, 10174568256, 10174568251], "tags": {"aeroway": "helipad"}}, {"type": "way", "id": 1122822285, "center": {"lat": 46.5203058, "lon": -60.4242412}, "nodes": [10268991225, 10268991224, 10268991223, 10268991222, 10268991225], "tags": {"aeroway": "helipad", "name": "Wreck Cove Hydro \u2013 Helipad", "operator": "Nova Scotia Power"}}, {"type": "way", "id": 1124044326, "center": {"lat": 47.7613378, "lon": -69.5823901}, "nodes": [10279274641, 10279274642, 10279274643, 10279274644, 10279274645, 10279274646, 10279274647, 10279274648, 10279274649, 10279274650, 10279274651, 10279274652, 10279274653, 10279274654, 10279274655, 10279274656, 10279274657, 10279274658, 10279274659, 10279274618, 10279274619, 10279274620, 10279274621, 10279274622, 10279274629, 10279274630, 10279274631, 10279274632, 10279274633, 10279274634, 10279274635, 10279274636, 10279274637, 10279274638, 10279274639, 10279274640, 10279274623, 10279274624, 10279274625, 10279274626, 10279274627, 10279274628, 10279274641], "tags": {"aeroway": "helipad"}}, {"type": "way", "id": 1149803058, "center": {"lat": 47.8489981, "lon": -69.5422666}, "nodes": [10696282759, 10696282760, 10696282761, 10696282762, 10696282763, 644339592, 10696282764, 10696282759], "tags": {"aeroway": "helipad"}}, {"type": "way", "id": 1206500741, "center": {"lat": 46.7805415, "lon": -67.8184609}, "nodes": [11179754051, 11179754052, 11179754053, 11179754054, 11179754051], "tags": {"aeroway": "helipad", "surface": "paved"}}, {"type": "way", "id": 1217568030, "center": {"lat": 48.1490985, "lon": -69.2386187}, "nodes": [11281652663, 11281652664, 11281652665, 11281652666, 11281652663], "tags": {"aeroway": "helipad"}}]}