[{"_id": "626148da1eacded7b7bb581c", "name": "SALME", "icaoCode": "EESE", "type": 7, "trafficType": [0], "magneticDeclination": 8.368, "country": "EE", "geometry": {"type": "Point", "coordinates": [22.258333333333, 58.131944444444]}, "elevation": {"value": 1, "unit": 0, "referenceDatum": 1}, "ppr": false, "private": false, "skydiveActivity": false, "winchOnly": false, "createdAt": "2022-04-21T12:06:50.997Z", "updatedAt": "2022-10-20T10:55:38.201Z", "createdBy": "AUTO-IMPORTER", "updatedBy": "openaip-system", "elevationGeoid": {"geoidHeight": 20.312625000000622, "hae": 21.312625000000622}}, {"_id": "626148db1eacded7b7bb5840", "name": "TALLINN CITYHALL", "icaoCode": "EECL", "type": 7, "trafficType": [0], "magneticDeclination": 9.62, "country": "EE", "geometry": {"type": "Point", "coordinates": [24.753333333333, 59.448055555556]}, "elevation": {"value": 7, "unit": 0, "referenceDatum": 1}, "ppr": false, "private": false, "skydiveActivity": false, "winchOnly": false, "createdAt": "2022-04-21T12:06:51.271Z", "updatedAt": "2022-10-20T10:55:38.384Z", "createdBy": "AUTO-IMPORTER", "updatedBy": "openaip-system", "elevationGeoid": {"geoidHeight": 18.169624799999255, "hae": 25.169624799999255}}]